setup.py
ndt_probability/Binomialdistribution.py
ndt_probability/Gaussiandistribution.py
ndt_probability/Generaldistribution.py
ndt_probability/__init__.py
ndt_probability.egg-info/PKG-INFO
ndt_probability.egg-info/SOURCES.txt
ndt_probability.egg-info/dependency_links.txt
ndt_probability.egg-info/not-zip-safe
ndt_probability.egg-info/top_level.txt