Metadata-Version: 1.0
Name: ndt-probability
Version: 0.1
Summary: Gaussian and Binomial distributions
Home-page: UNKNOWN
Author: Nilesh T
Author-email: test@test.com
License: UNKNOWN
Platform: UNKNOWN
